example_mas/__init__.py
example_mas/mosaik.py
example_sim/__init__.py
example_sim/mosaik.py
example_sim/simulator.py
mosaik_api_v3/__init__.py
mosaik_api_v3/connection.py
mosaik_api_v3/datetime.py
mosaik_api_v3/py.typed
mosaik_api_v3/types.py
mosaik_api_v3-3.0.14.dist-info/METADATA
mosaik_api_v3-3.0.14.dist-info/WHEEL
mosaik_api_v3-3.0.14.dist-info/entry_points.txt
mosaik_api_v3-3.0.14.dist-info/licenses/AUTHORS.txt
mosaik_api_v3-3.0.14.dist-info/licenses/LICENSE.txt
mosaik_api_v3-3.0.14.dist-info/RECORD
