Metadata-Version: 2.4
Name: mosaik-api-v3
Version: 3.0.14
Summary: Python implementation of the mosaik API, version 3
Project-URL: Homepage, https://mosaik.offis.de
Project-URL: Repository, https://gitlab.com/mosaik/api/mosaik-api-python
Author-email: mosaik development team <mosaik@offis.de>
License: MIT License
License-File: AUTHORS.txt
License-File: LICENSE.txt
Classifier: Development Status :: 5 - Production/Stable
Classifier: Environment :: Console
Classifier: Intended Audience :: Science/Research
Classifier: License :: OSI Approved :: MIT License
Classifier: Natural Language :: English
Classifier: Operating System :: OS Independent
Classifier: Programming Language :: Python
Classifier: Programming Language :: Python :: 3
Classifier: Programming Language :: Python :: 3.8
Classifier: Programming Language :: Python :: 3.9
Classifier: Programming Language :: Python :: 3.10
Classifier: Programming Language :: Python :: 3.11
Classifier: Topic :: Scientific/Engineering
Classifier: Topic :: Software Development :: Libraries :: Python Modules
Requires-Python: >=3.8
Requires-Dist: docopt>=0.6.1
Requires-Dist: loguru>=0.6.0
Requires-Dist: typing-extensions>=4.4.0
